setup.py
brightone_hangman/__init__.py
brightone_hangman/__main__.py
brightone_hangman/easy
brightone_hangman/game.py
brightone_hangman/hard
brightone_hangman/man.py
brightone_hangman/medium
brightone_hangman.egg-info/PKG-INFO
brightone_hangman.egg-info/SOURCES.txt
brightone_hangman.egg-info/dependency_links.txt
brightone_hangman.egg-info/not-zip-safe
brightone_hangman.egg-info/top_level.txt