Metadata-Version: 1.0
Name: brightone-hangman
Version: 0.2
Summary: Simple hangman game
Home-page: UNKNOWN
Author: filalex77
Author-email: filalex77@gmail.com
License: MIT
Platform: UNKNOWN
